ogctests/__init__.py
ogctests/__main__.py
ogctests/conftest.py
ogctests/features/__init__.py
ogctests/features/core/__init__.py
ogctests/features/core/conftest.py
ogctests/features/core/test_apidefinition.py
ogctests/features/core/test_collection.py
ogctests/features/core/test_collections.py
ogctests/features/core/test_conformance.py
ogctests/features/core/test_crs.py
ogctests/features/core/test_errorconditions.py
ogctests/features/core/test_feature.py
ogctests/features/core/test_features.py
ogctests/features/core/test_general.py
ogctests/features/core/test_landingpage.py
ogctests/features/core/utils.py
ogctests/features/filtering/__init__.py
ogctests/features/filtering/conftest.py
ogctests/features/filtering/test_filter.py
ogctests/features/filtering/test_queryables.py
ogctests/features/filtering/test_queryables_query_parameters.py
ogctests/features/filtering/utils.py
ogctests/features/schemas/bbox.yaml
ogctests/features/schemas/collection.yaml
ogctests/features/schemas/collections.yaml
ogctests/features/schemas/confClasses.yaml
ogctests/features/schemas/datetime.yaml
ogctests/features/schemas/extent.yaml
ogctests/features/schemas/featureCollectionGeoJSON.yaml
ogctests/features/schemas/featureGeoJSON.yaml
ogctests/features/schemas/geometryGeoJSON.yaml
ogctests/features/schemas/geometrycollectionGeoJSON.yaml
ogctests/features/schemas/landingPage.yaml
ogctests/features/schemas/limit.yaml
ogctests/features/schemas/linestringGeoJSON.yaml
ogctests/features/schemas/link.yaml
ogctests/features/schemas/multilinestringGeoJSON.yaml
ogctests/features/schemas/multipointGeoJSON.yaml
ogctests/features/schemas/multipolygonGeoJSON.yaml
ogctests/features/schemas/openapi_schema_v3.0.yaml
ogctests/features/schemas/pointGeoJSON.yaml
ogctests/features/schemas/polygonGeoJSON.yaml
ogctests/main.py
ogctests-0.1.15.dist-info/METADATA
ogctests-0.1.15.dist-info/WHEEL
ogctests-0.1.15.dist-info/RECORD
