Metadata-Version: 2.1
Name: ogctests
Version: 0.1.15
Summary:  [WIP] A black box verifier for the OGC API Specification
Author: Lawson Lewis
Author-email: lawson@kurrawong.ai
Requires-Python: >=3.11,<4.0
Classifier: Programming Language :: Python :: 3
Classifier: Programming Language :: Python :: 3.11
Classifier: Programming Language :: Python :: 3.12
Requires-Dist: geopandas (>=1.0.1,<2.0.0)
Requires-Dist: httpx (>=0.27.0,<0.28.0)
Requires-Dist: openapi-schema-validator (>=0.6.2,<0.7.0)
Requires-Dist: pyarrow (>=17.0.0,<18.0.0)
Requires-Dist: pytest (>=8.3.2,<9.0.0)
Requires-Dist: pyyaml (>=6.0.1,<7.0.0)
Requires-Dist: respx (>=0.21.1,<0.22.0)
